ggf/__init__.py
ggf/_version.py
ggf/_version_save.py
ggf/core.py
ggf/matlab_funcs.py
ggf/sci_funcs.py
ggf/lut/__init__.py
ggf/lut/lut_guck_all_cell.h5
ggf/lut/lut_guck_open_fus.h5
ggf/stress/__init__.py
ggf/stress/geometry.py
ggf/stress/boyde2009/__init__.py
ggf/stress/boyde2009/core.py
ggf/stress/boyde2009/globgeomfact.py
ggf/stress/boyde2009/hypergeomdata2.dat
ggf-0.4.0.dist-info/DESCRIPTION.rst
ggf-0.4.0.dist-info/LICENSE.txt
ggf-0.4.0.dist-info/METADATA
ggf-0.4.0.dist-info/RECORD
ggf-0.4.0.dist-info/WHEEL
ggf-0.4.0.dist-info/metadata.json
ggf-0.4.0.dist-info/top_level.txt
