Metadata-Version: 2.0
Name: ggf
Version: 0.4.0
Summary: global geometric factors and corresponding stresses of the optical stretcher 
Home-page: https://github.com/GuckLab/ggf
Author: Paul Müller
Author-email: dev@craban.de
License: MIT
Keywords: optical stretcher,global geometric factor
Platform: ALL
Classifier: Operating System :: OS Independent
Classifier: Programming Language :: Python :: 3
Classifier: Intended Audience :: Science/Research
Requires-Python: >=3.6, <4
Requires-Dist: h5py (>=2.7.0numpy>=1.9.0)
Requires-Dist: scipy (>=0.18.0)
